{
"type": "FeatureCollection",
"name": "center",
"crs": { "type": "name", "properties": { "name": "urn:ogc:def:crs:OGC:1.3:CRS84" } },
"features": [
{ "type": "Feature", "properties": { "id": "Columbia University ", "latitude": 40.8075, "longitude": -73.9626 }, "geometry": { "type": "Point", "coordinates": [ -73.9626, 40.8075 ] } }
]
}
